{
    "@context": "http://iiif.io/api/presentation/2/context.json",
    "@id": "https://readux2.ecdsdev.org/iiif/v2/17447788.4942.emory.edu/list/17447788.4942.emory.edu$118",
    "@type": "sc:AnnotationList",
    "resources": [
        {
            "@context": "http://iiif.io/api/presentation/2/context.json",
            "@id": "b5975d19-95e4-4a28-af0e-69da05266bce",
            "@type": "oa:Annotation",
            "motivation": "sc:painting",
            "annotatedBy": {
                "name": "OCR"
            },
            "resource": {
                "@type": "cnt:ContentAsText",
                "format": "text/html",
                "chars": "<span id='b5975d19-95e4-4a28-af0e-69da05266bce' data-letter-spacing='0.18530701754385967'>Een</span>",
                "language": "en"
            },
            "on": {
                "full": "https://readux2.ecdsdev.org/iiif/v2/17447788.4942.emory.edu/canvas/17447788.4942.emory.edu$118",
                "@type": "oa:SpecificResource",
                "within": {
                    "@id": "https://readux2.ecdsdev.org/iiif/v2/17447788.4942.emory.edu/manifest",
                    "@type": "sc:Manifest"
                },
                "selector": {
                    "@type": "oa:FragmentSelector",
                    "value": "xywh=721,272,76,36",
                    "item": {
                        "@type": "oa:FragmentSelector"
                    }
                }
            },
            "stylesheet": {
                "type": "CssStylesheet",
                "value": ".anno-b5975d19-95e4-4a28-af0e-69da05266bce: { height: 36px; width: 76px; font-size: 22.5px; }"
            }
        },
        {
            "@context": "http://iiif.io/api/presentation/2/context.json",
            "@id": "3b1e7a7c-46d4-4d8b-96f1-bcb3102a1846",
            "@type": "oa:Annotation",
            "motivation": "sc:painting",
            "annotatedBy": {
                "name": "OCR"
            },
            "resource": {
                "@type": "cnt:ContentAsText",
                "format": "text/html",
                "chars": "<span id='3b1e7a7c-46d4-4d8b-96f1-bcb3102a1846' data-letter-spacing='0.03236914600550964'>fuyuer</span>",
                "language": "en"
            },
            "on": {
                "full": "https://readux2.ecdsdev.org/iiif/v2/17447788.4942.emory.edu/canvas/17447788.4942.emory.edu$118",
                "@type": "oa:SpecificResource",
                "within": {
                    "@id": "https://readux2.ecdsdev.org/iiif/v2/17447788.4942.emory.edu/manifest",
                    "@type": "sc:Manifest"
                },
                "selector": {
                    "@type": "oa:FragmentSelector",
                    "value": "xywh=810,266,121,52",
                    "item": {
                        "@type": "oa:FragmentSelector"
                    }
                }
            },
            "stylesheet": {
                "type": "CssStylesheet",
                "value": ".anno-3b1e7a7c-46d4-4d8b-96f1-bcb3102a1846: { height: 52px; width: 121px; font-size: 32.5px; }"
            }
        },
        {
            "@context": "http://iiif.io/api/presentation/2/context.json",
            "@id": "64c8c235-9e79-4b6c-8a1d-d35deed09e85",
            "@type": "oa:Annotation",
            "motivation": "sc:painting",
            "annotatedBy": {
                "name": "OCR"
            },
            "resource": {
                "@type": "cnt:ContentAsText",
                "format": "text/html",
                "chars": "<span id='64c8c235-9e79-4b6c-8a1d-d35deed09e85' data-letter-spacing='0.10176282051282051'>hete</span>",
                "language": "en"
            },
            "on": {
                "full": "https://readux2.ecdsdev.org/iiif/v2/17447788.4942.emory.edu/canvas/17447788.4942.emory.edu$118",
                "@type": "oa:SpecificResource",
                "within": {
                    "@id": "https://readux2.ecdsdev.org/iiif/v2/17447788.4942.emory.edu/manifest",
                    "@type": "sc:Manifest"
                },
                "selector": {
                    "@type": "oa:FragmentSelector",
                    "value": "xywh=948,266,78,37",
                    "item": {
                        "@type": "oa:FragmentSelector"
                    }
                }
            },
            "stylesheet": {
                "type": "CssStylesheet",
                "value": ".anno-64c8c235-9e79-4b6c-8a1d-d35deed09e85: { height: 37px; width: 78px; font-size: 23.125px; }"
            }
        },
        {
            "@context": "http://iiif.io/api/presentation/2/context.json",
            "@id": "d8246651-b4cc-4eeb-a7a7-504fcb07c772",
            "@type": "oa:Annotation",
            "motivation": "sc:painting",
            "annotatedBy": {
                "name": "OCR"
            },
            "resource": {
                "@type": "cnt:ContentAsText",
                "format": "text/html",
                "chars": "<span id='d8246651-b4cc-4eeb-a7a7-504fcb07c772' data-letter-spacing='0.04032258064516129'>verbeelt</span>",
                "language": "en"
            },
            "on": {
                "full": "https://readux2.ecdsdev.org/iiif/v2/17447788.4942.emory.edu/canvas/17447788.4942.emory.edu$118",
                "@type": "oa:SpecificResource",
                "within": {
                    "@id": "https://readux2.ecdsdev.org/iiif/v2/17447788.4942.emory.edu/manifest",
                    "@type": "sc:Manifest"
                },
                "selector": {
                    "@type": "oa:FragmentSelector",
                    "value": "xywh=1039,263,155,42",
                    "item": {
                        "@type": "oa:FragmentSelector"
                    }
                }
            },
            "stylesheet": {
                "type": "CssStylesheet",
                "value": ".anno-d8246651-b4cc-4eeb-a7a7-504fcb07c772: { height: 42px; width: 155px; font-size: 26.25px; }"
            }
        },
        {
            "@context": "http://iiif.io/api/presentation/2/context.json",
            "@id": "fa4ad1e1-bd0d-409b-aebe-186d2b86cdf0",
            "@type": "oa:Annotation",
            "motivation": "sc:painting",
            "annotatedBy": {
                "name": "OCR"
            },
            "resource": {
                "@type": "cnt:ContentAsText",
                "format": "text/html",
                "chars": "<span id='fa4ad1e1-bd0d-409b-aebe-186d2b86cdf0' data-letter-spacing='0.09491150442477876'>Godr\u00bb</span>",
                "language": "en"
            },
            "on": {
                "full": "https://readux2.ecdsdev.org/iiif/v2/17447788.4942.emory.edu/canvas/17447788.4942.emory.edu$118",
                "@type": "oa:SpecificResource",
                "within": {
                    "@id": "https://readux2.ecdsdev.org/iiif/v2/17447788.4942.emory.edu/manifest",
                    "@type": "sc:Manifest"
                },
                "selector": {
                    "@type": "oa:FragmentSelector",
                    "value": "xywh=1209,263,113,38",
                    "item": {
                        "@type": "oa:FragmentSelector"
                    }
                }
            },
            "stylesheet": {
                "type": "CssStylesheet",
                "value": ".anno-fa4ad1e1-bd0d-409b-aebe-186d2b86cdf0: { height: 38px; width: 113px; font-size: 23.75px; }"
            }
        },
        {
            "@context": "http://iiif.io/api/presentation/2/context.json",
            "@id": "3488f60f-b510-4207-82df-67ceb1b5c699",
            "@type": "oa:Annotation",
            "motivation": "sc:painting",
            "annotatedBy": {
                "name": "OCR"
            },
            "resource": {
                "@type": "cnt:ContentAsText",
                "format": "text/html",
                "chars": "<span id='3488f60f-b510-4207-82df-67ceb1b5c699' data-letter-spacing='0.625'>a</span>",
                "language": "en"
            },
            "on": {
                "full": "https://readux2.ecdsdev.org/iiif/v2/17447788.4942.emory.edu/canvas/17447788.4942.emory.edu$118",
                "@type": "oa:SpecificResource",
                "within": {
                    "@id": "https://readux2.ecdsdev.org/iiif/v2/17447788.4942.emory.edu/manifest",
                    "@type": "sc:Manifest"
                },
                "selector": {
                    "@type": "oa:FragmentSelector",
                    "value": "xywh=679,1290,10,12",
                    "item": {
                        "@type": "oa:FragmentSelector"
                    }
                }
            },
            "stylesheet": {
                "type": "CssStylesheet",
                "value": ".anno-3488f60f-b510-4207-82df-67ceb1b5c699: { height: 12px; width: 10px; font-size: 7.5px; }"
            }
        },
        {
            "@context": "http://iiif.io/api/presentation/2/context.json",
            "@id": "c8add7a4-87ee-47a7-a43b-d4f05e92a15a",
            "@type": "oa:Annotation",
            "motivation": "sc:painting",
            "annotatedBy": {
                "name": "OCR"
            },
            "resource": {
                "@type": "cnt:ContentAsText",
                "format": "text/html",
                "chars": "<span id='c8add7a4-87ee-47a7-a43b-d4f05e92a15a' data-letter-spacing='0.34375'>rr</span>",
                "language": "en"
            },
            "on": {
                "full": "https://readux2.ecdsdev.org/iiif/v2/17447788.4942.emory.edu/canvas/17447788.4942.emory.edu$118",
                "@type": "oa:SpecificResource",
                "within": {
                    "@id": "https://readux2.ecdsdev.org/iiif/v2/17447788.4942.emory.edu/manifest",
                    "@type": "sc:Manifest"
                },
                "selector": {
                    "@type": "oa:FragmentSelector",
                    "value": "xywh=704,1288,28,14",
                    "item": {
                        "@type": "oa:FragmentSelector"
                    }
                }
            },
            "stylesheet": {
                "type": "CssStylesheet",
                "value": ".anno-c8add7a4-87ee-47a7-a43b-d4f05e92a15a: { height: 14px; width: 28px; font-size: 8.75px; }"
            }
        },
        {
            "@context": "http://iiif.io/api/presentation/2/context.json",
            "@id": "3cf4070c-2ee3-4cb2-91fe-db7849ca7f72",
            "@type": "oa:Annotation",
            "motivation": "sc:painting",
            "annotatedBy": {
                "name": "OCR"
            },
            "resource": {
                "@type": "cnt:ContentAsText",
                "format": "text/html",
                "chars": "<span id='3cf4070c-2ee3-4cb2-91fe-db7849ca7f72' data-letter-spacing='0.33035714285714285'>i</span>",
                "language": "en"
            },
            "on": {
                "full": "https://readux2.ecdsdev.org/iiif/v2/17447788.4942.emory.edu/canvas/17447788.4942.emory.edu$118",
                "@type": "oa:SpecificResource",
                "within": {
                    "@id": "https://readux2.ecdsdev.org/iiif/v2/17447788.4942.emory.edu/manifest",
                    "@type": "sc:Manifest"
                },
                "selector": {
                    "@type": "oa:FragmentSelector",
                    "value": "xywh=782,1287,7,15",
                    "item": {
                        "@type": "oa:FragmentSelector"
                    }
                }
            },
            "stylesheet": {
                "type": "CssStylesheet",
                "value": ".anno-3cf4070c-2ee3-4cb2-91fe-db7849ca7f72: { height: 15px; width: 7px; font-size: 9.375px; }"
            }
        },
        {
            "@context": "http://iiif.io/api/presentation/2/context.json",
            "@id": "6cab9489-06aa-4fa4-86f9-6ddee03d2d63",
            "@type": "oa:Annotation",
            "motivation": "sc:painting",
            "annotatedBy": {
                "name": "OCR"
            },
            "resource": {
                "@type": "cnt:ContentAsText",
                "format": "text/html",
                "chars": "<span id='6cab9489-06aa-4fa4-86f9-6ddee03d2d63' data-letter-spacing='0.2727272727272727'>ft</span>",
                "language": "en"
            },
            "on": {
                "full": "https://readux2.ecdsdev.org/iiif/v2/17447788.4942.emory.edu/canvas/17447788.4942.emory.edu$118",
                "@type": "oa:SpecificResource",
                "within": {
                    "@id": "https://readux2.ecdsdev.org/iiif/v2/17447788.4942.emory.edu/manifest",
                    "@type": "sc:Manifest"
                },
                "selector": {
                    "@type": "oa:FragmentSelector",
                    "value": "xywh=971,1286,22,16",
                    "item": {
                        "@type": "oa:FragmentSelector"
                    }
                }
            },
            "stylesheet": {
                "type": "CssStylesheet",
                "value": ".anno-6cab9489-06aa-4fa4-86f9-6ddee03d2d63: { height: 16px; width: 22px; font-size: 10.0px; }"
            }
        },
        {
            "@context": "http://iiif.io/api/presentation/2/context.json",
            "@id": "576de88c-bfcd-47aa-a4cf-5a50b0a16256",
            "@type": "oa:Annotation",
            "motivation": "sc:painting",
            "annotatedBy": {
                "name": "OCR"
            },
            "resource": {
                "@type": "cnt:ContentAsText",
                "format": "text/html",
                "chars": "<span id='576de88c-bfcd-47aa-a4cf-5a50b0a16256' data-letter-spacing='0.37664473684210525'>tv</span>",
                "language": "en"
            },
            "on": {
                "full": "https://readux2.ecdsdev.org/iiif/v2/17447788.4942.emory.edu/canvas/17447788.4942.emory.edu$118",
                "@type": "oa:SpecificResource",
                "within": {
                    "@id": "https://readux2.ecdsdev.org/iiif/v2/17447788.4942.emory.edu/manifest",
                    "@type": "sc:Manifest"
                },
                "selector": {
                    "@type": "oa:FragmentSelector",
                    "value": "xywh=1023,1287,38,15",
                    "item": {
                        "@type": "oa:FragmentSelector"
                    }
                }
            },
            "stylesheet": {
                "type": "CssStylesheet",
                "value": ".anno-576de88c-bfcd-47aa-a4cf-5a50b0a16256: { height: 15px; width: 38px; font-size: 9.375px; }"
            }
        },
        {
            "@context": "http://iiif.io/api/presentation/2/context.json",
            "@id": "aa3439ad-2329-4482-9a7f-75020f288222",
            "@type": "oa:Annotation",
            "motivation": "sc:painting",
            "annotatedBy": {
                "name": "OCR"
            },
            "resource": {
                "@type": "cnt:ContentAsText",
                "format": "text/html",
                "chars": "<span id='aa3439ad-2329-4482-9a7f-75020f288222' data-letter-spacing='0.3080357142857143'>f</span>",
                "language": "en"
            },
            "on": {
                "full": "https://readux2.ecdsdev.org/iiif/v2/17447788.4942.emory.edu/canvas/17447788.4942.emory.edu$118",
                "@type": "oa:SpecificResource",
                "within": {
                    "@id": "https://readux2.ecdsdev.org/iiif/v2/17447788.4942.emory.edu/manifest",
                    "@type": "sc:Manifest"
                },
                "selector": {
                    "@type": "oa:FragmentSelector",
                    "value": "xywh=1179,1271,14,31",
                    "item": {
                        "@type": "oa:FragmentSelector"
                    }
                }
            },
            "stylesheet": {
                "type": "CssStylesheet",
                "value": ".anno-aa3439ad-2329-4482-9a7f-75020f288222: { height: 31px; width: 14px; font-size: 19.375px; }"
            }
        },
        {
            "@context": "http://iiif.io/api/presentation/2/context.json",
            "@id": "cf63048f-acc7-405a-bcca-55bf9e29a6a8",
            "@type": "oa:Annotation",
            "motivation": "sc:painting",
            "annotatedBy": {
                "name": "OCR"
            },
            "resource": {
                "@type": "cnt:ContentAsText",
                "format": "text/html",
                "chars": "<span id='cf63048f-acc7-405a-bcca-55bf9e29a6a8' data-letter-spacing='0.11538461538461539'>Hier</span>",
                "language": "en"
            },
            "on": {
                "full": "https://readux2.ecdsdev.org/iiif/v2/17447788.4942.emory.edu/canvas/17447788.4942.emory.edu$118",
                "@type": "oa:SpecificResource",
                "within": {
                    "@id": "https://readux2.ecdsdev.org/iiif/v2/17447788.4942.emory.edu/manifest",
                    "@type": "sc:Manifest"
                },
                "selector": {
                    "@type": "oa:FragmentSelector",
                    "value": "xywh=1216,1267,65,28",
                    "item": {
                        "@type": "oa:FragmentSelector"
                    }
                }
            },
            "stylesheet": {
                "type": "CssStylesheet",
                "value": ".anno-cf63048f-acc7-405a-bcca-55bf9e29a6a8: { height: 28px; width: 65px; font-size: 17.5px; }"
            }
        },
        {
            "@context": "http://iiif.io/api/presentation/2/context.json",
            "@id": "5e05ccf6-2a09-4a3b-935b-83f3239be2c8",
            "@type": "oa:Annotation",
            "motivation": "sc:painting",
            "annotatedBy": {
                "name": "OCR"
            },
            "resource": {
                "@type": "cnt:ContentAsText",
                "format": "text/html",
                "chars": "<span id='5e05ccf6-2a09-4a3b-935b-83f3239be2c8' data-letter-spacing='0.01050420168067227'>(heelt-</span>",
                "language": "en"
            },
            "on": {
                "full": "https://readux2.ecdsdev.org/iiif/v2/17447788.4942.emory.edu/canvas/17447788.4942.emory.edu$118",
                "@type": "oa:SpecificResource",
                "within": {
                    "@id": "https://readux2.ecdsdev.org/iiif/v2/17447788.4942.emory.edu/manifest",
                    "@type": "sc:Manifest"
                },
                "selector": {
                    "@type": "oa:FragmentSelector",
                    "value": "xywh=1292,1266,85,36",
                    "item": {
                        "@type": "oa:FragmentSelector"
                    }
                }
            },
            "stylesheet": {
                "type": "CssStylesheet",
                "value": ".anno-5e05ccf6-2a09-4a3b-935b-83f3239be2c8: { height: 36px; width: 85px; font-size: 22.5px; }"
            }
        },
        {
            "@context": "http://iiif.io/api/presentation/2/context.json",
            "@id": "2e646c21-f598-4743-9268-7db6f59d8042",
            "@type": "oa:Annotation",
            "motivation": "sc:painting",
            "annotatedBy": {
                "name": "OCR"
            },
            "resource": {
                "@type": "cnt:ContentAsText",
                "format": "text/html",
                "chars": "<span id='2e646c21-f598-4743-9268-7db6f59d8042' data-letter-spacing='0.05443548387096774'>Affimdat</span>",
                "language": "en"
            },
            "on": {
                "full": "https://readux2.ecdsdev.org/iiif/v2/17447788.4942.emory.edu/canvas/17447788.4942.emory.edu$118",
                "@type": "oa:SpecificResource",
                "within": {
                    "@id": "https://readux2.ecdsdev.org/iiif/v2/17447788.4942.emory.edu/manifest",
                    "@type": "sc:Manifest"
                },
                "selector": {
                    "@type": "oa:FragmentSelector",
                    "value": "xywh=668,1289,155,35",
                    "item": {
                        "@type": "oa:FragmentSelector"
                    }
                }
            },
            "stylesheet": {
                "type": "CssStylesheet",
                "value": ".anno-2e646c21-f598-4743-9268-7db6f59d8042: { height: 35px; width: 155px; font-size: 21.875px; }"
            }
        },
        {
            "@context": "http://iiif.io/api/presentation/2/context.json",
            "@id": "e15f29f9-e4e5-45fc-9146-2d073dd7b790",
            "@type": "oa:Annotation",
            "motivation": "sc:painting",
            "annotatedBy": {
                "name": "OCR"
            },
            "resource": {
                "@type": "cnt:ContentAsText",
                "format": "text/html",
                "chars": "<span id='e15f29f9-e4e5-45fc-9146-2d073dd7b790' data-letter-spacing='0.17279411764705882'>mens</span>",
                "language": "en"
            },
            "on": {
                "full": "https://readux2.ecdsdev.org/iiif/v2/17447788.4942.emory.edu/canvas/17447788.4942.emory.edu$118",
                "@type": "oa:SpecificResource",
                "within": {
                    "@id": "https://readux2.ecdsdev.org/iiif/v2/17447788.4942.emory.edu/manifest",
                    "@type": "sc:Manifest"
                },
                "selector": {
                    "@type": "oa:FragmentSelector",
                    "value": "xywh=836,1300,85,21",
                    "item": {
                        "@type": "oa:FragmentSelector"
                    }
                }
            },
            "stylesheet": {
                "type": "CssStylesheet",
                "value": ".anno-e15f29f9-e4e5-45fc-9146-2d073dd7b790: { height: 21px; width: 85px; font-size: 13.125px; }"
            }
        },
        {
            "@context": "http://iiif.io/api/presentation/2/context.json",
            "@id": "0d1bf613-1334-421d-8b17-c2e9ab1f2bfb",
            "@type": "oa:Annotation",
            "motivation": "sc:painting",
            "annotatedBy": {
                "name": "OCR"
            },
            "resource": {
                "@type": "cnt:ContentAsText",
                "format": "text/html",
                "chars": "<span id='0d1bf613-1334-421d-8b17-c2e9ab1f2bfb' data-letter-spacing='0.075'>cafia</span>",
                "language": "en"
            },
            "on": {
                "full": "https://readux2.ecdsdev.org/iiif/v2/17447788.4942.emory.edu/canvas/17447788.4942.emory.edu$118",
                "@type": "oa:SpecificResource",
                "within": {
                    "@id": "https://readux2.ecdsdev.org/iiif/v2/17447788.4942.emory.edu/manifest",
                    "@type": "sc:Manifest"
                },
                "selector": {
                    "@type": "oa:FragmentSelector",
                    "value": "xywh=933,1289,80,32",
                    "item": {
                        "@type": "oa:FragmentSelector"
                    }
                }
            },
            "stylesheet": {
                "type": "CssStylesheet",
                "value": ".anno-0d1bf613-1334-421d-8b17-c2e9ab1f2bfb: { height: 32px; width: 80px; font-size: 20.0px; }"
            }
        },
        {
            "@context": "http://iiif.io/api/presentation/2/context.json",
            "@id": "42e3f13c-4f94-4d9a-9390-dcb5a9c190d7",
            "@type": "oa:Annotation",
            "motivation": "sc:painting",
            "annotatedBy": {
                "name": "OCR"
            },
            "resource": {
                "@type": "cnt:ContentAsText",
                "format": "text/html",
                "chars": "<span id='42e3f13c-4f94-4d9a-9390-dcb5a9c190d7' data-letter-spacing='0.11918103448275862'>Deum.</span>",
                "language": "en"
            },
            "on": {
                "full": "https://readux2.ecdsdev.org/iiif/v2/17447788.4942.emory.edu/canvas/17447788.4942.emory.edu$118",
                "@type": "oa:SpecificResource",
                "within": {
                    "@id": "https://readux2.ecdsdev.org/iiif/v2/17447788.4942.emory.edu/manifest",
                    "@type": "sc:Manifest"
                },
                "selector": {
                    "@type": "oa:FragmentSelector",
                    "value": "xywh=1023,1289,116,30",
                    "item": {
                        "@type": "oa:FragmentSelector"
                    }
                }
            },
            "stylesheet": {
                "type": "CssStylesheet",
                "value": ".anno-42e3f13c-4f94-4d9a-9390-dcb5a9c190d7: { height: 30px; width: 116px; font-size: 18.75px; }"
            }
        },
        {
            "@context": "http://iiif.io/api/presentation/2/context.json",
            "@id": "fb566768-411a-4376-b2f8-90bd4ac838a5",
            "@type": "oa:Annotation",
            "motivation": "sc:painting",
            "annotatedBy": {
                "name": "OCR"
            },
            "resource": {
                "@type": "cnt:ContentAsText",
                "format": "text/html",
                "chars": "<span id='fb566768-411a-4376-b2f8-90bd4ac838a5' data-letter-spacing='0.2708333333333333'>j</span>",
                "language": "en"
            },
            "on": {
                "full": "https://readux2.ecdsdev.org/iiif/v2/17447788.4942.emory.edu/canvas/17447788.4942.emory.edu$118",
                "@type": "oa:SpecificResource",
                "within": {
                    "@id": "https://readux2.ecdsdev.org/iiif/v2/17447788.4942.emory.edu/manifest",
                    "@type": "sc:Manifest"
                },
                "selector": {
                    "@type": "oa:FragmentSelector",
                    "value": "xywh=1171,1289,21,49",
                    "item": {
                        "@type": "oa:FragmentSelector"
                    }
                }
            },
            "stylesheet": {
                "type": "CssStylesheet",
                "value": ".anno-fb566768-411a-4376-b2f8-90bd4ac838a5: { height: 49px; width: 21px; font-size: 30.625px; }"
            }
        },
        {
            "@context": "http://iiif.io/api/presentation/2/context.json",
            "@id": "d276937d-177c-427a-a629-a8e5eb73f11a",
            "@type": "oa:Annotation",
            "motivation": "sc:painting",
            "annotatedBy": {
                "name": "OCR"
            },
            "resource": {
                "@type": "cnt:ContentAsText",
                "format": "text/html",
                "chars": "<span id='d276937d-177c-427a-a629-a8e5eb73f11a' data-letter-spacing='0.08782051282051281'>codts</span>",
                "language": "en"
            },
            "on": {
                "full": "https://readux2.ecdsdev.org/iiif/v2/17447788.4942.emory.edu/canvas/17447788.4942.emory.edu$118",
                "@type": "oa:SpecificResource",
                "within": {
                    "@id": "https://readux2.ecdsdev.org/iiif/v2/17447788.4942.emory.edu/manifest",
                    "@type": "sc:Manifest"
                },
                "selector": {
                    "@type": "oa:FragmentSelector",
                    "value": "xywh=1222,1306,78,28",
                    "item": {
                        "@type": "oa:FragmentSelector"
                    }
                }
            },
            "stylesheet": {
                "type": "CssStylesheet",
                "value": ".anno-d276937d-177c-427a-a629-a8e5eb73f11a: { height: 28px; width: 78px; font-size: 17.5px; }"
            }
        },
        {
            "@context": "http://iiif.io/api/presentation/2/context.json",
            "@id": "40363219-e826-4fda-b424-55fbb745cb45",
            "@type": "oa:Annotation",
            "motivation": "sc:painting",
            "annotatedBy": {
                "name": "OCR"
            },
            "resource": {
                "@type": "cnt:ContentAsText",
                "format": "text/html",
                "chars": "<span id='40363219-e826-4fda-b424-55fbb745cb45' data-letter-spacing='0.04842342342342343'>beelt.</span>",
                "language": "en"
            },
            "on": {
                "full": "https://readux2.ecdsdev.org/iiif/v2/17447788.4942.emory.edu/canvas/17447788.4942.emory.edu$118",
                "@type": "oa:SpecificResource",
                "within": {
                    "@id": "https://readux2.ecdsdev.org/iiif/v2/17447788.4942.emory.edu/manifest",
                    "@type": "sc:Manifest"
                },
                "selector": {
                    "@type": "oa:FragmentSelector",
                    "value": "xywh=1312,1305,74,28",
                    "item": {
                        "@type": "oa:FragmentSelector"
                    }
                }
            },
            "stylesheet": {
                "type": "CssStylesheet",
                "value": ".anno-40363219-e826-4fda-b424-55fbb745cb45: { height: 28px; width: 74px; font-size: 17.5px; }"
            }
        },
        {
            "@context": "http://iiif.io/api/presentation/2/context.json",
            "@id": "47db8348-6412-411d-892f-76c5d4fa0b7a",
            "@type": "oa:Annotation",
            "motivation": "sc:painting",
            "annotatedBy": {
                "name": "OCR"
            },
            "resource": {
                "@type": "cnt:ContentAsText",
                "format": "text/html",
                "chars": "<span id='47db8348-6412-411d-892f-76c5d4fa0b7a' data-letter-spacing='0.7443181818181818'>T</span>",
                "language": "en"
            },
            "on": {
                "full": "https://readux2.ecdsdev.org/iiif/v2/17447788.4942.emory.edu/canvas/17447788.4942.emory.edu$118",
                "@type": "oa:SpecificResource",
                "within": {
                    "@id": "https://readux2.ecdsdev.org/iiif/v2/17447788.4942.emory.edu/manifest",
                    "@type": "sc:Manifest"
                },
                "selector": {
                    "@type": "oa:FragmentSelector",
                    "value": "xywh=858,1380,33,27",
                    "item": {
                        "@type": "oa:FragmentSelector"
                    }
                }
            },
            "stylesheet": {
                "type": "CssStylesheet",
                "value": ".anno-47db8348-6412-411d-892f-76c5d4fa0b7a: { height: 27px; width: 33px; font-size: 16.875px; }"
            }
        },
        {
            "@context": "http://iiif.io/api/presentation/2/context.json",
            "@id": "2465ec18-a0df-468c-9dce-3a9fd4d4a77c",
            "@type": "oa:Annotation",
            "motivation": "sc:painting",
            "annotatedBy": {
                "name": "OCR"
            },
            "resource": {
                "@type": "cnt:ContentAsText",
                "format": "text/html",
                "chars": "<span id='2465ec18-a0df-468c-9dce-3a9fd4d4a77c' data-letter-spacing='0.1875'>een</span>",
                "language": "en"
            },
            "on": {
                "full": "https://readux2.ecdsdev.org/iiif/v2/17447788.4942.emory.edu/canvas/17447788.4942.emory.edu$118",
                "@type": "oa:SpecificResource",
                "within": {
                    "@id": "https://readux2.ecdsdev.org/iiif/v2/17447788.4942.emory.edu/manifest",
                    "@type": "sc:Manifest"
                },
                "selector": {
                    "@type": "oa:FragmentSelector",
                    "value": "xywh=910,1386,45,21",
                    "item": {
                        "@type": "oa:FragmentSelector"
                    }
                }
            },
            "stylesheet": {
                "type": "CssStylesheet",
                "value": ".anno-2465ec18-a0df-468c-9dce-3a9fd4d4a77c: { height: 21px; width: 45px; font-size: 13.125px; }"
            }
        },
        {
            "@context": "http://iiif.io/api/presentation/2/context.json",
            "@id": "7634b6a7-6c9c-4bc1-8e6a-c09a4457da1e",
            "@type": "oa:Annotation",
            "motivation": "sc:painting",
            "annotatedBy": {
                "name": "OCR"
            },
            "resource": {
                "@type": "cnt:ContentAsText",
                "format": "text/html",
                "chars": "<span id='7634b6a7-6c9c-4bc1-8e6a-c09a4457da1e' data-letter-spacing='0.013813405797101448'>foeten</span>",
                "language": "en"
            },
            "on": {
                "full": "https://readux2.ecdsdev.org/iiif/v2/17447788.4942.emory.edu/canvas/17447788.4942.emory.edu$118",
                "@type": "oa:SpecificResource",
                "within": {
                    "@id": "https://readux2.ecdsdev.org/iiif/v2/17447788.4942.emory.edu/manifest",
                    "@type": "sc:Manifest"
                },
                "selector": {
                    "@type": "oa:FragmentSelector",
                    "value": "xywh=968,1371,92,45",
                    "item": {
                        "@type": "oa:FragmentSelector"
                    }
                }
            },
            "stylesheet": {
                "type": "CssStylesheet",
                "value": ".anno-7634b6a7-6c9c-4bc1-8e6a-c09a4457da1e: { height: 45px; width: 92px; font-size: 28.125px; }"
            }
        },
        {
            "@context": "http://iiif.io/api/presentation/2/context.json",
            "@id": "7e294804-607e-4e94-817b-951f37e7b261",
            "@type": "oa:Annotation",
            "motivation": "sc:painting",
            "annotatedBy": {
                "name": "OCR"
            },
            "resource": {
                "@type": "cnt:ContentAsText",
                "format": "text/html",
                "chars": "<span id='7e294804-607e-4e94-817b-951f37e7b261' data-letter-spacing='0.0296681664791901'>morghen</span>",
                "language": "en"
            },
            "on": {
                "full": "https://readux2.ecdsdev.org/iiif/v2/17447788.4942.emory.edu/canvas/17447788.4942.emory.edu$118",
                "@type": "oa:SpecificResource",
                "within": {
                    "@id": "https://readux2.ecdsdev.org/iiif/v2/17447788.4942.emory.edu/manifest",
                    "@type": "sc:Manifest"
                },
                "selector": {
                    "@type": "oa:FragmentSelector",
                    "value": "xywh=1075,1370,127,46",
                    "item": {
                        "@type": "oa:FragmentSelector"
                    }
                }
            },
            "stylesheet": {
                "type": "CssStylesheet",
                "value": ".anno-7e294804-607e-4e94-817b-951f37e7b261: { height: 46px; width: 127px; font-size: 28.75px; }"
            }
        },
        {
            "@context": "http://iiif.io/api/presentation/2/context.json",
            "@id": "bf54f224-967e-4255-b4ac-0c7c09091b26",
            "@type": "oa:Annotation",
            "motivation": "sc:painting",
            "annotatedBy": {
                "name": "OCR"
            },
            "resource": {
                "@type": "cnt:ContentAsText",
                "format": "text/html",
                "chars": "<span id='bf54f224-967e-4255-b4ac-0c7c09091b26' data-letter-spacing='0.0055907877169559415'>flondt,</span>",
                "language": "en"
            },
            "on": {
                "full": "https://readux2.ecdsdev.org/iiif/v2/17447788.4942.emory.edu/canvas/17447788.4942.emory.edu$118",
                "@type": "oa:SpecificResource",
                "within": {
                    "@id": "https://readux2.ecdsdev.org/iiif/v2/17447788.4942.emory.edu/manifest",
                    "@type": "sc:Manifest"
                },
                "selector": {
                    "@type": "oa:FragmentSelector",
                    "value": "xywh=1213,1367,107,47",
                    "item": {
                        "@type": "oa:FragmentSelector"
                    }
                }
            },
            "stylesheet": {
                "type": "CssStylesheet",
                "value": ".anno-bf54f224-967e-4255-b4ac-0c7c09091b26: { height: 47px; width: 107px; font-size: 29.375px; }"
            }
        },
        {
            "@context": "http://iiif.io/api/presentation/2/context.json",
            "@id": "edd64cb5-9cc4-4ecf-846b-2f17e04f0f90",
            "@type": "oa:Annotation",
            "motivation": "sc:painting",
            "annotatedBy": {
                "name": "OCR"
            },
            "resource": {
                "@type": "cnt:ContentAsText",
                "format": "text/html",
                "chars": "<span id='edd64cb5-9cc4-4ecf-846b-2f17e04f0f90' data-letter-spacing='-0.3125'>'</span>",
                "language": "en"
            },
            "on": {
                "full": "https://readux2.ecdsdev.org/iiif/v2/17447788.4942.emory.edu/canvas/17447788.4942.emory.edu$118",
                "@type": "oa:SpecificResource",
                "within": {
                    "@id": "https://readux2.ecdsdev.org/iiif/v2/17447788.4942.emory.edu/manifest",
                    "@type": "sc:Manifest"
                },
                "selector": {
                    "@type": "oa:FragmentSelector",
                    "value": "xywh=838,1418,5,21",
                    "item": {
                        "@type": "oa:FragmentSelector"
                    }
                }
            },
            "stylesheet": {
                "type": "CssStylesheet",
                "value": ".anno-edd64cb5-9cc4-4ecf-846b-2f17e04f0f90: { height: 21px; width: 5px; font-size: 13.125px; }"
            }
        },
        {
            "@context": "http://iiif.io/api/presentation/2/context.json",
            "@id": "7e546730-e11f-4350-aec3-3606b2ae234b",
            "@type": "oa:Annotation",
            "motivation": "sc:painting",
            "annotatedBy": {
                "name": "OCR"
            },
            "resource": {
                "@type": "cnt:ContentAsText",
                "format": "text/html",
                "chars": "<span id='7e546730-e11f-4350-aec3-3606b2ae234b' data-letter-spacing='0.1556372549019608'>Soo</span>",
                "language": "en"
            },
            "on": {
                "full": "https://readux2.ecdsdev.org/iiif/v2/17447788.4942.emory.edu/canvas/17447788.4942.emory.edu$118",
                "@type": "oa:SpecificResource",
                "within": {
                    "@id": "https://readux2.ecdsdev.org/iiif/v2/17447788.4942.emory.edu/manifest",
                    "@type": "sc:Manifest"
                },
                "selector": {
                    "@type": "oa:FragmentSelector",
                    "value": "xywh=857,1425,51,29",
                    "item": {
                        "@type": "oa:FragmentSelector"
                    }
                }
            },
            "stylesheet": {
                "type": "CssStylesheet",
                "value": ".anno-7e546730-e11f-4350-aec3-3606b2ae234b: { height: 29px; width: 51px; font-size: 18.125px; }"
            }
        },
        {
            "@context": "http://iiif.io/api/presentation/2/context.json",
            "@id": "6682a357-b7a4-4a92-b5ae-f4bca648106c",
            "@type": "oa:Annotation",
            "motivation": "sc:painting",
            "annotatedBy": {
                "name": "OCR"
            },
            "resource": {
                "@type": "cnt:ContentAsText",
                "format": "text/html",
                "chars": "<span id='6682a357-b7a4-4a92-b5ae-f4bca648106c' data-letter-spacing='-0.0625'>ick\\.</span>",
                "language": "en"
            },
            "on": {
                "full": "https://readux2.ecdsdev.org/iiif/v2/17447788.4942.emory.edu/canvas/17447788.4942.emory.edu$118",
                "@type": "oa:SpecificResource",
                "within": {
                    "@id": "https://readux2.ecdsdev.org/iiif/v2/17447788.4942.emory.edu/manifest",
                    "@type": "sc:Manifest"
                },
                "selector": {
                    "@type": "oa:FragmentSelector",
                    "value": "xywh=927,1418,50,42",
                    "item": {
                        "@type": "oa:FragmentSelector"
                    }
                }
            },
            "stylesheet": {
                "type": "CssStylesheet",
                "value": ".anno-6682a357-b7a4-4a92-b5ae-f4bca648106c: { height: 42px; width: 50px; font-size: 26.25px; }"
            }
        },
        {
            "@context": "http://iiif.io/api/presentation/2/context.json",
            "@id": "090188c3-16f1-405e-a8dc-6b5b139f8481",
            "@type": "oa:Annotation",
            "motivation": "sc:painting",
            "annotatedBy": {
                "name": "OCR"
            },
            "resource": {
                "@type": "cnt:ContentAsText",
                "format": "text/html",
                "chars": "<span id='090188c3-16f1-405e-a8dc-6b5b139f8481' data-letter-spacing='0.27982954545454547'>my</span>",
                "language": "en"
            },
            "on": {
                "full": "https://readux2.ecdsdev.org/iiif/v2/17447788.4942.emory.edu/canvas/17447788.4942.emory.edu$118",
                "@type": "oa:SpecificResource",
                "within": {
                    "@id": "https://readux2.ecdsdev.org/iiif/v2/17447788.4942.emory.edu/manifest",
                    "@type": "sc:Manifest"
                },
                "selector": {
                    "@type": "oa:FragmentSelector",
                    "value": "xywh=985,1432,44,31",
                    "item": {
                        "@type": "oa:FragmentSelector"
                    }
                }
            },
            "stylesheet": {
                "type": "CssStylesheet",
                "value": ".anno-090188c3-16f1-405e-a8dc-6b5b139f8481: { height: 31px; width: 44px; font-size: 19.375px; }"
            }
        },
        {
            "@context": "http://iiif.io/api/presentation/2/context.json",
            "@id": "cfc3e168-ab3b-4246-bbb1-04c5948a4324",
            "@type": "oa:Annotation",
            "motivation": "sc:painting",
            "annotatedBy": {
                "name": "OCR"
            },
            "resource": {
                "@type": "cnt:ContentAsText",
                "format": "text/html",
                "chars": "<span id='cfc3e168-ab3b-4246-bbb1-04c5948a4324' data-letter-spacing='0.08217213114754099'>Tt>*t</span>",
                "language": "en"
            },
            "on": {
                "full": "https://readux2.ecdsdev.org/iiif/v2/17447788.4942.emory.edu/canvas/17447788.4942.emory.edu$118",
                "@type": "oa:SpecificResource",
                "within": {
                    "@id": "https://readux2.ecdsdev.org/iiif/v2/17447788.4942.emory.edu/manifest",
                    "@type": "sc:Manifest"
                },
                "selector": {
                    "@type": "oa:FragmentSelector",
                    "value": "xywh=1045,1427,61,23",
                    "item": {
                        "@type": "oa:FragmentSelector"
                    }
                }
            },
            "stylesheet": {
                "type": "CssStylesheet",
                "value": ".anno-cfc3e168-ab3b-4246-bbb1-04c5948a4324: { height: 23px; width: 61px; font-size: 14.375px; }"
            }
        },
        {
            "@context": "http://iiif.io/api/presentation/2/context.json",
            "@id": "9d7c82dc-69b9-4237-86a2-3836e86cd931",
            "@type": "oa:Annotation",
            "motivation": "sc:painting",
            "annotatedBy": {
                "name": "OCR"
            },
            "resource": {
                "@type": "cnt:ContentAsText",
                "format": "text/html",
                "chars": "<span id='9d7c82dc-69b9-4237-86a2-3836e86cd931' data-letter-spacing='-0.0021551724137931034'>ledigh</span>",
                "language": "en"
            },
            "on": {
                "full": "https://readux2.ecdsdev.org/iiif/v2/17447788.4942.emory.edu/canvas/17447788.4942.emory.edu$118",
                "@type": "oa:SpecificResource",
                "within": {
                    "@id": "https://readux2.ecdsdev.org/iiif/v2/17447788.4942.emory.edu/manifest",
                    "@type": "sc:Manifest"
                },
                "selector": {
                    "@type": "oa:FragmentSelector",
                    "value": "xywh=1122,1416,87,47",
                    "item": {
                        "@type": "oa:FragmentSelector"
                    }
                }
            },
            "stylesheet": {
                "type": "CssStylesheet",
                "value": ".anno-9d7c82dc-69b9-4237-86a2-3836e86cd931: { height: 47px; width: 87px; font-size: 29.375px; }"
            }
        },
        {
            "@context": "http://iiif.io/api/presentation/2/context.json",
            "@id": "7f69c08b-08f2-4a1f-966e-148bef56eacc",
            "@type": "oa:Annotation",
            "motivation": "sc:painting",
            "annotatedBy": {
                "name": "OCR"
            },
            "resource": {
                "@type": "cnt:ContentAsText",
                "format": "text/html",
                "chars": "<span id='7f69c08b-08f2-4a1f-966e-148bef56eacc' data-letter-spacing='0.028006715506715508'>nsondt^</span>",
                "language": "en"
            },
            "on": {
                "full": "https://readux2.ecdsdev.org/iiif/v2/17447788.4942.emory.edu/canvas/17447788.4942.emory.edu$118",
                "@type": "oa:SpecificResource",
                "within": {
                    "@id": "https://readux2.ecdsdev.org/iiif/v2/17447788.4942.emory.edu/manifest",
                    "@type": "sc:Manifest"
                },
                "selector": {
                    "@type": "oa:FragmentSelector",
                    "value": "xywh=1230,1413,117,43",
                    "item": {
                        "@type": "oa:FragmentSelector"
                    }
                }
            },
            "stylesheet": {
                "type": "CssStylesheet",
                "value": ".anno-7f69c08b-08f2-4a1f-966e-148bef56eacc: { height: 43px; width: 117px; font-size: 26.875px; }"
            }
        },
        {
            "@context": "http://iiif.io/api/presentation/2/context.json",
            "@id": "6abb74e0-9852-4763-9f49-05318b652616",
            "@type": "oa:Annotation",
            "motivation": "sc:painting",
            "annotatedBy": {
                "name": "OCR"
            },
            "resource": {
                "@type": "cnt:ContentAsText",
                "format": "text/html",
                "chars": "<span id='6abb74e0-9852-4763-9f49-05318b652616' data-letter-spacing='0.03997747747747748'>Ghtngh</span>",
                "language": "en"
            },
            "on": {
                "full": "https://readux2.ecdsdev.org/iiif/v2/17447788.4942.emory.edu/canvas/17447788.4942.emory.edu$118",
                "@type": "oa:SpecificResource",
                "within": {
                    "@id": "https://readux2.ecdsdev.org/iiif/v2/17447788.4942.emory.edu/manifest",
                    "@type": "sc:Manifest"
                },
                "selector": {
                    "@type": "oa:FragmentSelector",
                    "value": "xywh=749,1469,111,45",
                    "item": {
                        "@type": "oa:FragmentSelector"
                    }
                }
            },
            "stylesheet": {
                "type": "CssStylesheet",
                "value": ".anno-6abb74e0-9852-4763-9f49-05318b652616: { height: 45px; width: 111px; font-size: 28.125px; }"
            }
        },
        {
            "@context": "http://iiif.io/api/presentation/2/context.json",
            "@id": "baa774ea-0d82-44bb-b274-e4889001d3e8",
            "@type": "oa:Annotation",
            "motivation": "sc:painting",
            "annotatedBy": {
                "name": "OCR"
            },
            "resource": {
                "@type": "cnt:ContentAsText",
                "format": "text/html",
                "chars": "<span id='baa774ea-0d82-44bb-b274-e4889001d3e8' data-letter-spacing='0.036595394736842105'>uitreden</span>",
                "language": "en"
            },
            "on": {
                "full": "https://readux2.ecdsdev.org/iiif/v2/17447788.4942.emory.edu/canvas/17447788.4942.emory.edu$118",
                "@type": "oa:SpecificResource",
                "within": {
                    "@id": "https://readux2.ecdsdev.org/iiif/v2/17447788.4942.emory.edu/manifest",
                    "@type": "sc:Manifest"
                },
                "selector": {
                    "@type": "oa:FragmentSelector",
                    "value": "xywh=878,1465,152,43",
                    "item": {
                        "@type": "oa:FragmentSelector"
                    }
                }
            },
            "stylesheet": {
                "type": "CssStylesheet",
                "value": ".anno-baa774ea-0d82-44bb-b274-e4889001d3e8: { height: 43px; width: 152px; font-size: 26.875px; }"
            }
        },
        {
            "@context": "http://iiif.io/api/presentation/2/context.json",
            "@id": "ed67db70-094c-481d-a1b1-195d937cf8c6",
            "@type": "oa:Annotation",
            "motivation": "sc:painting",
            "annotatedBy": {
                "name": "OCR"
            },
            "resource": {
                "@type": "cnt:ContentAsText",
                "format": "text/html",
                "chars": "<span id='ed67db70-094c-481d-a1b1-195d937cf8c6' data-letter-spacing='0.21215986394557823'>aen</span>",
                "language": "en"
            },
            "on": {
                "full": "https://readux2.ecdsdev.org/iiif/v2/17447788.4942.emory.edu/canvas/17447788.4942.emory.edu$118",
                "@type": "oa:SpecificResource",
                "within": {
                    "@id": "https://readux2.ecdsdev.org/iiif/v2/17447788.4942.emory.edu/manifest",
                    "@type": "sc:Manifest"
                },
                "selector": {
                    "@type": "oa:FragmentSelector",
                    "value": "xywh=1048,1477,49,19",
                    "item": {
                        "@type": "oa:FragmentSelector"
                    }
                }
            },
            "stylesheet": {
                "type": "CssStylesheet",
                "value": ".anno-ed67db70-094c-481d-a1b1-195d937cf8c6: { height: 19px; width: 49px; font-size: 11.875px; }"
            }
        },
        {
            "@context": "http://iiif.io/api/presentation/2/context.json",
            "@id": "7d4f4ef6-a51c-419d-8975-29432ca58104",
            "@type": "oa:Annotation",
            "motivation": "sc:painting",
            "annotatedBy": {
                "name": "OCR"
            },
            "resource": {
                "@type": "cnt:ContentAsText",
                "format": "text/html",
                "chars": "<span id='7d4f4ef6-a51c-419d-8975-29432ca58104' data-letter-spacing='0.17803030303030304'>de</span>",
                "language": "en"
            },
            "on": {
                "full": "https://readux2.ecdsdev.org/iiif/v2/17447788.4942.emory.edu/canvas/17447788.4942.emory.edu$118",
                "@type": "oa:SpecificResource",
                "within": {
                    "@id": "https://readux2.ecdsdev.org/iiif/v2/17447788.4942.emory.edu/manifest",
                    "@type": "sc:Manifest"
                },
                "selector": {
                    "@type": "oa:FragmentSelector",
                    "value": "xywh=1113,1462,33,34",
                    "item": {
                        "@type": "oa:FragmentSelector"
                    }
                }
            },
            "stylesheet": {
                "type": "CssStylesheet",
                "value": ".anno-7d4f4ef6-a51c-419d-8975-29432ca58104: { height: 34px; width: 33px; font-size: 21.25px; }"
            }
        },
        {
            "@context": "http://iiif.io/api/presentation/2/context.json",
            "@id": "fe4515a7-0fba-440a-b159-0a43cefbf53b",
            "@type": "oa:Annotation",
            "motivation": "sc:painting",
            "annotatedBy": {
                "name": "OCR"
            },
            "resource": {
                "@type": "cnt:ContentAsText",
                "format": "text/html",
                "chars": "<span id='fe4515a7-0fba-440a-b159-0a43cefbf53b' data-letter-spacing='0.0693359375'>kant</span>",
                "language": "en"
            },
            "on": {
                "full": "https://readux2.ecdsdev.org/iiif/v2/17447788.4942.emory.edu/canvas/17447788.4942.emory.edu$118",
                "@type": "oa:SpecificResource",
                "within": {
                    "@id": "https://readux2.ecdsdev.org/iiif/v2/17447788.4942.emory.edu/manifest",
                    "@type": "sc:Manifest"
                },
                "selector": {
                    "@type": "oa:FragmentSelector",
                    "value": "xywh=1163,1462,64,37",
                    "item": {
                        "@type": "oa:FragmentSelector"
                    }
                }
            },
            "stylesheet": {
                "type": "CssStylesheet",
                "value": ".anno-fe4515a7-0fba-440a-b159-0a43cefbf53b: { height: 37px; width: 64px; font-size: 23.125px; }"
            }
        },
        {
            "@context": "http://iiif.io/api/presentation/2/context.json",
            "@id": "81c7cacd-ce15-4132-9448-389c3ce35b2f",
            "@type": "oa:Annotation",
            "motivation": "sc:painting",
            "annotatedBy": {
                "name": "OCR"
            },
            "resource": {
                "@type": "cnt:ContentAsText",
                "format": "text/html",
                "chars": "<span id='81c7cacd-ce15-4132-9448-389c3ce35b2f' data-letter-spacing='0.18212365591397847'>Van</span>",
                "language": "en"
            },
            "on": {
                "full": "https://readux2.ecdsdev.org/iiif/v2/17447788.4942.emory.edu/canvas/17447788.4942.emory.edu$118",
                "@type": "oa:SpecificResource",
                "within": {
                    "@id": "https://readux2.ecdsdev.org/iiif/v2/17447788.4942.emory.edu/manifest",
                    "@type": "sc:Manifest"
                },
                "selector": {
                    "@type": "oa:FragmentSelector",
                    "value": "xywh=747,1520,62,30",
                    "item": {
                        "@type": "oa:FragmentSelector"
                    }
                }
            },
            "stylesheet": {
                "type": "CssStylesheet",
                "value": ".anno-81c7cacd-ce15-4132-9448-389c3ce35b2f: { height: 30px; width: 62px; font-size: 18.75px; }"
            }
        },
        {
            "@context": "http://iiif.io/api/presentation/2/context.json",
            "@id": "20956180-f44f-4d43-9760-2c845adb7003",
            "@type": "oa:Annotation",
            "motivation": "sc:painting",
            "annotatedBy": {
                "name": "OCR"
            },
            "resource": {
                "@type": "cnt:ContentAsText",
                "format": "text/html",
                "chars": "<span id='20956180-f44f-4d43-9760-2c845adb7003' data-letter-spacing='0.1227355072463768'>bet</span>",
                "language": "en"
            },
            "on": {
                "full": "https://readux2.ecdsdev.org/iiif/v2/17447788.4942.emory.edu/canvas/17447788.4942.emory.edu$118",
                "@type": "oa:SpecificResource",
                "within": {
                    "@id": "https://readux2.ecdsdev.org/iiif/v2/17447788.4942.emory.edu/manifest",
                    "@type": "sc:Manifest"
                },
                "selector": {
                    "@type": "oa:FragmentSelector",
                    "value": "xywh=825,1517,46,31",
                    "item": {
                        "@type": "oa:FragmentSelector"
                    }
                }
            },
            "stylesheet": {
                "type": "CssStylesheet",
                "value": ".anno-20956180-f44f-4d43-9760-2c845adb7003: { height: 31px; width: 46px; font-size: 19.375px; }"
            }
        },
        {
            "@context": "http://iiif.io/api/presentation/2/context.json",
            "@id": "fc2ea032-390f-4ed1-a8e4-d5daab0e5ba5",
            "@type": "oa:Annotation",
            "motivation": "sc:painting",
            "annotatedBy": {
                "name": "OCR"
            },
            "resource": {
                "@type": "cnt:ContentAsText",
                "format": "text/html",
                "chars": "<span id='fc2ea032-390f-4ed1-a8e4-d5daab0e5ba5' data-letter-spacing='0.06918604651162791'>groen</span>",
                "language": "en"
            },
            "on": {
                "full": "https://readux2.ecdsdev.org/iiif/v2/17447788.4942.emory.edu/canvas/17447788.4942.emory.edu$118",
                "@type": "oa:SpecificResource",
                "within": {
                    "@id": "https://readux2.ecdsdev.org/iiif/v2/17447788.4942.emory.edu/manifest",
                    "@type": "sc:Manifest"
                },
                "selector": {
                    "@type": "oa:FragmentSelector",
                    "value": "xywh=882,1527,86,36",
                    "item": {
                        "@type": "oa:FragmentSelector"
                    }
                }
            },
            "stylesheet": {
                "type": "CssStylesheet",
                "value": ".anno-fc2ea032-390f-4ed1-a8e4-d5daab0e5ba5: { height: 36px; width: 86px; font-size: 22.5px; }"
            }
        },
        {
            "@context": "http://iiif.io/api/presentation/2/context.json",
            "@id": "760a4a24-b257-4ef4-9f0f-244a1478ef77",
            "@type": "oa:Annotation",
            "motivation": "sc:painting",
            "annotatedBy": {
                "name": "OCR"
            },
            "resource": {
                "@type": "cnt:ContentAsText",
                "format": "text/html",
                "chars": "<span id='760a4a24-b257-4ef4-9f0f-244a1478ef77' data-letter-spacing='0.0036949685534591195'>gbeklauert</span>",
                "language": "en"
            },
            "on": {
                "full": "https://readux2.ecdsdev.org/iiif/v2/17447788.4942.emory.edu/canvas/17447788.4942.emory.edu$118",
                "@type": "oa:SpecificResource",
                "within": {
                    "@id": "https://readux2.ecdsdev.org/iiif/v2/17447788.4942.emory.edu/manifest",
                    "@type": "sc:Manifest"
                },
                "selector": {
                    "@type": "oa:FragmentSelector",
                    "value": "xywh=979,1510,159,49",
                    "item": {
                        "@type": "oa:FragmentSelector"
                    }
                }
            },
            "stylesheet": {
                "type": "CssStylesheet",
                "value": ".anno-760a4a24-b257-4ef4-9f0f-244a1478ef77: { height: 49px; width: 159px; font-size: 30.625px; }"
            }
        },
        {
            "@context": "http://iiif.io/api/presentation/2/context.json",
            "@id": "57bc5c43-6318-42df-94ba-5cd60ad19745",
            "@type": "oa:Annotation",
            "motivation": "sc:painting",
            "annotatedBy": {
                "name": "OCR"
            },
            "resource": {
                "@type": "cnt:ContentAsText",
                "format": "text/html",
                "chars": "<span id='57bc5c43-6318-42df-94ba-5cd60ad19745' data-letter-spacing='0.05241935483870968'>landt:</span>",
                "language": "en"
            },
            "on": {
                "full": "https://readux2.ecdsdev.org/iiif/v2/17447788.4942.emory.edu/canvas/17447788.4942.emory.edu$118",
                "@type": "oa:SpecificResource",
                "within": {
                    "@id": "https://readux2.ecdsdev.org/iiif/v2/17447788.4942.emory.edu/manifest",
                    "@type": "sc:Manifest"
                },
                "selector": {
                    "@type": "oa:FragmentSelector",
                    "value": "xywh=1157,1508,93,34",
                    "item": {
                        "@type": "oa:FragmentSelector"
                    }
                }
            },
            "stylesheet": {
                "type": "CssStylesheet",
                "value": ".anno-57bc5c43-6318-42df-94ba-5cd60ad19745: { height: 34px; width: 93px; font-size: 21.25px; }"
            }
        },
        {
            "@context": "http://iiif.io/api/presentation/2/context.json",
            "@id": "a73cb811-1a42-441e-a084-5f9432001732",
            "@type": "oa:Annotation",
            "motivation": "sc:painting",
            "annotatedBy": {
                "name": "OCR"
            },
            "resource": {
                "@type": "cnt:ContentAsText",
                "format": "text/html",
                "chars": "<span id='a73cb811-1a42-441e-a084-5f9432001732' data-letter-spacing='0.1798780487804878'>Op</span>",
                "language": "en"
            },
            "on": {
                "full": "https://readux2.ecdsdev.org/iiif/v2/17447788.4942.emory.edu/canvas/17447788.4942.emory.edu$118",
                "@type": "oa:SpecificResource",
                "within": {
                    "@id": "https://readux2.ecdsdev.org/iiif/v2/17447788.4942.emory.edu/manifest",
                    "@type": "sc:Manifest"
                },
                "selector": {
                    "@type": "oa:FragmentSelector",
                    "value": "xywh=747,1567,41,42",
                    "item": {
                        "@type": "oa:FragmentSelector"
                    }
                }
            },
            "stylesheet": {
                "type": "CssStylesheet",
                "value": ".anno-a73cb811-1a42-441e-a084-5f9432001732: { height: 42px; width: 41px; font-size: 26.25px; }"
            }
        },
        {
            "@context": "http://iiif.io/api/presentation/2/context.json",
            "@id": "8dded171-0203-42e0-847c-05fc4089a5a4",
            "@type": "oa:Annotation",
            "motivation": "sc:painting",
            "annotatedBy": {
                "name": "OCR"
            },
            "resource": {
                "@type": "cnt:ContentAsText",
                "format": "text/html",
                "chars": "<span id='8dded171-0203-42e0-847c-05fc4089a5a4' data-letter-spacing='0.12083333333333333'>den</span>",
                "language": "en"
            },
            "on": {
                "full": "https://readux2.ecdsdev.org/iiif/v2/17447788.4942.emory.edu/canvas/17447788.4942.emory.edu$118",
                "@type": "oa:SpecificResource",
                "within": {
                    "@id": "https://readux2.ecdsdev.org/iiif/v2/17447788.4942.emory.edu/manifest",
                    "@type": "sc:Manifest"
                },
                "selector": {
                    "@type": "oa:FragmentSelector",
                    "value": "xywh=804,1561,50,34",
                    "item": {
                        "@type": "oa:FragmentSelector"
                    }
                }
            },
            "stylesheet": {
                "type": "CssStylesheet",
                "value": ".anno-8dded171-0203-42e0-847c-05fc4089a5a4: { height: 34px; width: 50px; font-size: 21.25px; }"
            }
        },
        {
            "@context": "http://iiif.io/api/presentation/2/context.json",
            "@id": "3dc948c6-01ff-48a7-8418-3637b4619024",
            "@type": "oa:Annotation",
            "motivation": "sc:painting",
            "annotatedBy": {
                "name": "OCR"
            },
            "resource": {
                "@type": "cnt:ContentAsText",
                "format": "text/html",
                "chars": "<span id='3dc948c6-01ff-48a7-8418-3637b4619024' data-letter-spacing='0.060352233676975946'>boordt</span>",
                "language": "en"
            },
            "on": {
                "full": "https://readux2.ecdsdev.org/iiif/v2/17447788.4942.emory.edu/canvas/17447788.4942.emory.edu$118",
                "@type": "oa:SpecificResource",
                "within": {
                    "@id": "https://readux2.ecdsdev.org/iiif/v2/17447788.4942.emory.edu/manifest",
                    "@type": "sc:Manifest"
                },
                "selector": {
                    "@type": "oa:FragmentSelector",
                    "value": "xywh=875,1560,97,33",
                    "item": {
                        "@type": "oa:FragmentSelector"
                    }
                }
            },
            "stylesheet": {
                "type": "CssStylesheet",
                "value": ".anno-3dc948c6-01ff-48a7-8418-3637b4619024: { height: 33px; width: 97px; font-size: 20.625px; }"
            }
        },
        {
            "@context": "http://iiif.io/api/presentation/2/context.json",
            "@id": "78b3c653-ad8d-418a-a591-ca219f809ba3",
            "@type": "oa:Annotation",
            "motivation": "sc:painting",
            "annotatedBy": {
                "name": "OCR"
            },
            "resource": {
                "@type": "cnt:ContentAsText",
                "format": "text/html",
                "chars": "<span id='78b3c653-ad8d-418a-a591-ca219f809ba3' data-letter-spacing='0.24404761904761904'>wan</span>",
                "language": "en"
            },
            "on": {
                "full": "https://readux2.ecdsdev.org/iiif/v2/17447788.4942.emory.edu/canvas/17447788.4942.emory.edu$118",
                "@type": "oa:SpecificResource",
                "within": {
                    "@id": "https://readux2.ecdsdev.org/iiif/v2/17447788.4942.emory.edu/manifest",
                    "@type": "sc:Manifest"
                },
                "selector": {
                    "@type": "oa:FragmentSelector",
                    "value": "xywh=988,1571,70,20",
                    "item": {
                        "@type": "oa:FragmentSelector"
                    }
                }
            },
            "stylesheet": {
                "type": "CssStylesheet",
                "value": ".anno-78b3c653-ad8d-418a-a591-ca219f809ba3: { height: 20px; width: 70px; font-size: 12.5px; }"
            }
        },
        {
            "@context": "http://iiif.io/api/presentation/2/context.json",
            "@id": "40866395-520a-4eec-8544-c2e76423d65c",
            "@type": "oa:Annotation",
            "motivation": "sc:painting",
            "annotatedBy": {
                "name": "OCR"
            },
            "resource": {
                "@type": "cnt:ContentAsText",
                "format": "text/html",
                "chars": "<span id='40866395-520a-4eec-8544-c2e76423d65c' data-letter-spacing='0.1875'>een</span>",
                "language": "en"
            },
            "on": {
                "full": "https://readux2.ecdsdev.org/iiif/v2/17447788.4942.emory.edu/canvas/17447788.4942.emory.edu$118",
                "@type": "oa:SpecificResource",
                "within": {
                    "@id": "https://readux2.ecdsdev.org/iiif/v2/17447788.4942.emory.edu/manifest",
                    "@type": "sc:Manifest"
                },
                "selector": {
                    "@type": "oa:FragmentSelector",
                    "value": "xywh=1076,1570,45,21",
                    "item": {
                        "@type": "oa:FragmentSelector"
                    }
                }
            },
            "stylesheet": {
                "type": "CssStylesheet",
                "value": ".anno-40866395-520a-4eec-8544-c2e76423d65c: { height: 21px; width: 45px; font-size: 13.125px; }"
            }
        },
        {
            "@context": "http://iiif.io/api/presentation/2/context.json",
            "@id": "20e58179-2149-49ff-9989-3a4bca992e10",
            "@type": "oa:Annotation",
            "motivation": "sc:painting",
            "annotatedBy": {
                "name": "OCR"
            },
            "resource": {
                "@type": "cnt:ContentAsText",
                "format": "text/html",
                "chars": "<span id='20e58179-2149-49ff-9989-3a4bca992e10' data-letter-spacing='0.054966517857142856'>riuier,</span>",
                "language": "en"
            },
            "on": {
                "full": "https://readux2.ecdsdev.org/iiif/v2/17447788.4942.emory.edu/canvas/17447788.4942.emory.edu$118",
                "@type": "oa:SpecificResource",
                "within": {
                    "@id": "https://readux2.ecdsdev.org/iiif/v2/17447788.4942.emory.edu/manifest",
                    "@type": "sc:Manifest"
                },
                "selector": {
                    "@type": "oa:FragmentSelector",
                    "value": "xywh=1138,1570,96,27",
                    "item": {
                        "@type": "oa:FragmentSelector"
                    }
                }
            },
            "stylesheet": {
                "type": "CssStylesheet",
                "value": ".anno-20e58179-2149-49ff-9989-3a4bca992e10: { height: 27px; width: 96px; font-size: 16.875px; }"
            }
        },
        {
            "@context": "http://iiif.io/api/presentation/2/context.json",
            "@id": "5ef6d225-d242-4e3e-b236-52eb25a75b54",
            "@type": "oa:Annotation",
            "motivation": "sc:painting",
            "annotatedBy": {
                "name": "OCR"
            },
            "resource": {
                "@type": "cnt:ContentAsText",
                "format": "text/html",
                "chars": "<span id='5ef6d225-d242-4e3e-b236-52eb25a75b54' data-letter-spacing='0.17708333333333331'>Die</span>",
                "language": "en"
            },
            "on": {
                "full": "https://readux2.ecdsdev.org/iiif/v2/17447788.4942.emory.edu/canvas/17447788.4942.emory.edu$118",
                "@type": "oa:SpecificResource",
                "within": {
                    "@id": "https://readux2.ecdsdev.org/iiif/v2/17447788.4942.emory.edu/manifest",
                    "@type": "sc:Manifest"
                },
                "selector": {
                    "@type": "oa:FragmentSelector",
                    "value": "xywh=748,1614,56,28",
                    "item": {
                        "@type": "oa:FragmentSelector"
                    }
                }
            },
            "stylesheet": {
                "type": "CssStylesheet",
                "value": ".anno-5ef6d225-d242-4e3e-b236-52eb25a75b54: { height: 28px; width: 56px; font-size: 17.5px; }"
            }
        },
        {
            "@context": "http://iiif.io/api/presentation/2/context.json",
            "@id": "6e20b7d0-8572-4158-8f62-fd17acc8588b",
            "@type": "oa:Annotation",
            "motivation": "sc:painting",
            "annotatedBy": {
                "name": "OCR"
            },
            "resource": {
                "@type": "cnt:ContentAsText",
                "format": "text/html",
                "chars": "<span id='6e20b7d0-8572-4158-8f62-fd17acc8588b' data-letter-spacing='0.09615384615384616'>daer</span>",
                "language": "en"
            },
            "on": {
                "full": "https://readux2.ecdsdev.org/iiif/v2/17447788.4942.emory.edu/canvas/17447788.4942.emory.edu$118",
                "@type": "oa:SpecificResource",
                "within": {
                    "@id": "https://readux2.ecdsdev.org/iiif/v2/17447788.4942.emory.edu/manifest",
                    "@type": "sc:Manifest"
                },
                "selector": {
                    "@type": "oa:FragmentSelector",
                    "value": "xywh=822,1609,65,32",
                    "item": {
                        "@type": "oa:FragmentSelector"
                    }
                }
            },
            "stylesheet": {
                "type": "CssStylesheet",
                "value": ".anno-6e20b7d0-8572-4158-8f62-fd17acc8588b: { height: 32px; width: 65px; font-size: 20.0px; }"
            }
        },
        {
            "@context": "http://iiif.io/api/presentation/2/context.json",
            "@id": "ee45cede-797e-4408-813b-695eecc3cf14",
            "@type": "oa:Annotation",
            "motivation": "sc:painting",
            "annotatedBy": {
                "name": "OCR"
            },
            "resource": {
                "@type": "cnt:ContentAsText",
                "format": "text/html",
                "chars": "<span id='ee45cede-797e-4408-813b-695eecc3cf14' data-letter-spacing='0.046703296703296704'>nueckte</span>",
                "language": "en"
            },
            "on": {
                "full": "https://readux2.ecdsdev.org/iiif/v2/17447788.4942.emory.edu/canvas/17447788.4942.emory.edu$118",
                "@type": "oa:SpecificResource",
                "within": {
                    "@id": "https://readux2.ecdsdev.org/iiif/v2/17447788.4942.emory.edu/manifest",
                    "@type": "sc:Manifest"
                },
                "selector": {
                    "@type": "oa:FragmentSelector",
                    "value": "xywh=901,1604,117,36",
                    "item": {
                        "@type": "oa:FragmentSelector"
                    }
                }
            },
            "stylesheet": {
                "type": "CssStylesheet",
                "value": ".anno-ee45cede-797e-4408-813b-695eecc3cf14: { height: 36px; width: 117px; font-size: 22.5px; }"
            }
        },
        {
            "@context": "http://iiif.io/api/presentation/2/context.json",
            "@id": "8c92f30e-c98f-43bc-a161-3a2bb91ebafa",
            "@type": "oa:Annotation",
            "motivation": "sc:painting",
            "annotatedBy": {
                "name": "OCR"
            },
            "resource": {
                "@type": "cnt:ContentAsText",
                "format": "text/html",
                "chars": "<span id='8c92f30e-c98f-43bc-a161-3a2bb91ebafa' data-letter-spacing='0.007543103448275862'>foet</span>",
                "language": "en"
            },
            "on": {
                "full": "https://readux2.ecdsdev.org/iiif/v2/17447788.4942.emory.edu/canvas/17447788.4942.emory.edu$118",
                "@type": "oa:SpecificResource",
                "within": {
                    "@id": "https://readux2.ecdsdev.org/iiif/v2/17447788.4942.emory.edu/manifest",
                    "@type": "sc:Manifest"
                },
                "selector": {
                    "@type": "oa:FragmentSelector",
                    "value": "xywh=1034,1603,58,45",
                    "item": {
                        "@type": "oa:FragmentSelector"
                    }
                }
            },
            "stylesheet": {
                "type": "CssStylesheet",
                "value": ".anno-8c92f30e-c98f-43bc-a161-3a2bb91ebafa: { height: 45px; width: 58px; font-size: 28.125px; }"
            }
        },
        {
            "@context": "http://iiif.io/api/presentation/2/context.json",
            "@id": "6c046fae-fc54-404c-abf3-2609d518648c",
            "@type": "oa:Annotation",
            "motivation": "sc:painting",
            "annotatedBy": {
                "name": "OCR"
            },
            "resource": {
                "@type": "cnt:ContentAsText",
                "format": "text/html",
                "chars": "<span id='6c046fae-fc54-404c-abf3-2609d518648c' data-letter-spacing='0.030357142857142857'>getier,</span>",
                "language": "en"
            },
            "on": {
                "full": "https://readux2.ecdsdev.org/iiif/v2/17447788.4942.emory.edu/canvas/17447788.4942.emory.edu$118",
                "@type": "oa:SpecificResource",
                "within": {
                    "@id": "https://readux2.ecdsdev.org/iiif/v2/17447788.4942.emory.edu/manifest",
                    "@type": "sc:Manifest"
                },
                "selector": {
                    "@type": "oa:FragmentSelector",
                    "value": "xywh=1106,1614,100,36",
                    "item": {
                        "@type": "oa:FragmentSelector"
                    }
                }
            },
            "stylesheet": {
                "type": "CssStylesheet",
                "value": ".anno-6c046fae-fc54-404c-abf3-2609d518648c: { height: 36px; width: 100px; font-size: 22.5px; }"
            }
        },
        {
            "@context": "http://iiif.io/api/presentation/2/context.json",
            "@id": "def7c979-b26b-4096-855a-c06e312ca4df",
            "@type": "oa:Annotation",
            "motivation": "sc:painting",
            "annotatedBy": {
                "name": "OCR"
            },
            "resource": {
                "@type": "cnt:ContentAsText",
                "format": "text/html",
                "chars": "<span id='def7c979-b26b-4096-855a-c06e312ca4df' data-letter-spacing='0.18266369047619047'>Die</span>",
                "language": "en"
            },
            "on": {
                "full": "https://readux2.ecdsdev.org/iiif/v2/17447788.4942.emory.edu/canvas/17447788.4942.emory.edu$118",
                "@type": "oa:SpecificResource",
                "within": {
                    "@id": "https://readux2.ecdsdev.org/iiif/v2/17447788.4942.emory.edu/manifest",
                    "@type": "sc:Manifest"
                },
                "selector": {
                    "@type": "oa:FragmentSelector",
                    "value": "xywh=751,1662,56,27",
                    "item": {
                        "@type": "oa:FragmentSelector"
                    }
                }
            },
            "stylesheet": {
                "type": "CssStylesheet",
                "value": ".anno-def7c979-b26b-4096-855a-c06e312ca4df: { height: 27px; width: 56px; font-size: 16.875px; }"
            }
        },
        {
            "@context": "http://iiif.io/api/presentation/2/context.json",
            "@id": "39bf1d84-2052-46da-99f2-df14430a80d6",
            "@type": "oa:Annotation",
            "motivation": "sc:painting",
            "annotatedBy": {
                "name": "OCR"
            },
            "resource": {
                "@type": "cnt:ContentAsText",
                "format": "text/html",
                "chars": "<span id='39bf1d84-2052-46da-99f2-df14430a80d6' data-letter-spacing='0.0888671875'>daer</span>",
                "language": "en"
            },
            "on": {
                "full": "https://readux2.ecdsdev.org/iiif/v2/17447788.4942.emory.edu/canvas/17447788.4942.emory.edu$118",
                "@type": "oa:SpecificResource",
                "within": {
                    "@id": "https://readux2.ecdsdev.org/iiif/v2/17447788.4942.emory.edu/manifest",
                    "@type": "sc:Manifest"
                },
                "selector": {
                    "@type": "oa:FragmentSelector",
                    "value": "xywh=828,1655,64,33",
                    "item": {
                        "@type": "oa:FragmentSelector"
                    }
                }
            },
            "stylesheet": {
                "type": "CssStylesheet",
                "value": ".anno-39bf1d84-2052-46da-99f2-df14430a80d6: { height: 33px; width: 64px; font-size: 20.625px; }"
            }
        },
        {
            "@context": "http://iiif.io/api/presentation/2/context.json",
            "@id": "dad1724b-8543-45cd-aa4c-5890c01f4e73",
            "@type": "oa:Annotation",
            "motivation": "sc:painting",
            "annotatedBy": {
                "name": "OCR"
            },
            "resource": {
                "@type": "cnt:ContentAsText",
                "format": "text/html",
                "chars": "<span id='dad1724b-8543-45cd-aa4c-5890c01f4e73' data-letter-spacing='0.036077235772357726'>dlvaelde</span>",
                "language": "en"
            },
            "on": {
                "full": "https://readux2.ecdsdev.org/iiif/v2/17447788.4942.emory.edu/canvas/17447788.4942.emory.edu$118",
                "@type": "oa:SpecificResource",
                "within": {
                    "@id": "https://readux2.ecdsdev.org/iiif/v2/17447788.4942.emory.edu/manifest",
                    "@type": "sc:Manifest"
                },
                "selector": {
                    "@type": "oa:FragmentSelector",
                    "value": "xywh=912,1651,123,35",
                    "item": {
                        "@type": "oa:FragmentSelector"
                    }
                }
            },
            "stylesheet": {
                "type": "CssStylesheet",
                "value": ".anno-dad1724b-8543-45cd-aa4c-5890c01f4e73: { height: 35px; width: 123px; font-size: 21.875px; }"
            }
        },
        {
            "@context": "http://iiif.io/api/presentation/2/context.json",
            "@id": "47cd2b9c-2c8d-4a27-a598-bcda7397506d",
            "@type": "oa:Annotation",
            "motivation": "sc:painting",
            "annotatedBy": {
                "name": "OCR"
            },
            "resource": {
                "@type": "cnt:ContentAsText",
                "format": "text/html",
                "chars": "<span id='47cd2b9c-2c8d-4a27-a598-bcda7397506d' data-letter-spacing='0.19444444444444445'>met</span>",
                "language": "en"
            },
            "on": {
                "full": "https://readux2.ecdsdev.org/iiif/v2/17447788.4942.emory.edu/canvas/17447788.4942.emory.edu$118",
                "@type": "oa:SpecificResource",
                "within": {
                    "@id": "https://readux2.ecdsdev.org/iiif/v2/17447788.4942.emory.edu/manifest",
                    "@type": "sc:Manifest"
                },
                "selector": {
                    "@type": "oa:FragmentSelector",
                    "value": "xywh=1053,1660,54,24",
                    "item": {
                        "@type": "oa:FragmentSelector"
                    }
                }
            },
            "stylesheet": {
                "type": "CssStylesheet",
                "value": ".anno-47cd2b9c-2c8d-4a27-a598-bcda7397506d: { height: 24px; width: 54px; font-size: 15.0px; }"
            }
        },
        {
            "@context": "http://iiif.io/api/presentation/2/context.json",
            "@id": "e6b554bb-d3e9-4a07-bee2-b1e2ce3a8434",
            "@type": "oa:Annotation",
            "motivation": "sc:painting",
            "annotatedBy": {
                "name": "OCR"
            },
            "resource": {
                "@type": "cnt:ContentAsText",
                "format": "text/html",
                "chars": "<span id='e6b554bb-d3e9-4a07-bee2-b1e2ce3a8434' data-letter-spacing='0.09126984126984126'>baer</span>",
                "language": "en"
            },
            "on": {
                "full": "https://readux2.ecdsdev.org/iiif/v2/17447788.4942.emory.edu/canvas/17447788.4942.emory.edu$118",
                "@type": "oa:SpecificResource",
                "within": {
                    "@id": "https://readux2.ecdsdev.org/iiif/v2/17447788.4942.emory.edu/manifest",
                    "@type": "sc:Manifest"
                },
                "selector": {
                    "@type": "oa:FragmentSelector",
                    "value": "xywh=1130,1651,63,32",
                    "item": {
                        "@type": "oa:FragmentSelector"
                    }
                }
            },
            "stylesheet": {
                "type": "CssStylesheet",
                "value": ".anno-e6b554bb-d3e9-4a07-bee2-b1e2ce3a8434: { height: 32px; width: 63px; font-size: 20.0px; }"
            }
        },
        {
            "@context": "http://iiif.io/api/presentation/2/context.json",
            "@id": "6bdeff3d-917f-40ad-a333-bdfcad24286b",
            "@type": "oa:Annotation",
            "motivation": "sc:painting",
            "annotatedBy": {
                "name": "OCR"
            },
            "resource": {
                "@type": "cnt:ContentAsText",
                "format": "text/html",
                "chars": "<span id='6bdeff3d-917f-40ad-a333-bdfcad24286b' data-letter-spacing='0.02586206896551724'>ft</span>",
                "language": "en"
            },
            "on": {
                "full": "https://readux2.ecdsdev.org/iiif/v2/17447788.4942.emory.edu/canvas/17447788.4942.emory.edu$118",
                "@type": "oa:SpecificResource",
                "within": {
                    "@id": "https://readux2.ecdsdev.org/iiif/v2/17447788.4942.emory.edu/manifest",
                    "@type": "sc:Manifest"
                },
                "selector": {
                    "@type": "oa:FragmentSelector",
                    "value": "xywh=1201,1650,29,44",
                    "item": {
                        "@type": "oa:FragmentSelector"
                    }
                }
            },
            "stylesheet": {
                "type": "CssStylesheet",
                "value": ".anno-6bdeff3d-917f-40ad-a333-bdfcad24286b: { height: 44px; width: 29px; font-size: 27.5px; }"
            }
        },
        {
            "@context": "http://iiif.io/api/presentation/2/context.json",
            "@id": "60d78e35-71ba-41d0-9578-cb9ee939751d",
            "@type": "oa:Annotation",
            "motivation": "sc:painting",
            "annotatedBy": {
                "name": "OCR"
            },
            "resource": {
                "@type": "cnt:ContentAsText",
                "format": "text/html",
                "chars": "<span id='60d78e35-71ba-41d0-9578-cb9ee939751d' data-letter-spacing='0.15757042253521128'>room</span>",
                "language": "en"
            },
            "on": {
                "full": "https://readux2.ecdsdev.org/iiif/v2/17447788.4942.emory.edu/canvas/17447788.4942.emory.edu$118",
                "@type": "oa:SpecificResource",
                "within": {
                    "@id": "https://readux2.ecdsdev.org/iiif/v2/17447788.4942.emory.edu/manifest",
                    "@type": "sc:Manifest"
                },
                "selector": {
                    "@type": "oa:FragmentSelector",
                    "value": "xywh=1232,1663,71,21",
                    "item": {
                        "@type": "oa:FragmentSelector"
                    }
                }
            },
            "stylesheet": {
                "type": "CssStylesheet",
                "value": ".anno-60d78e35-71ba-41d0-9578-cb9ee939751d: { height: 21px; width: 71px; font-size: 13.125px; }"
            }
        },
        {
            "@context": "http://iiif.io/api/presentation/2/context.json",
            "@id": "335df2a5-7b86-49c5-8d09-bbdef1309c2e",
            "@type": "oa:Annotation",
            "motivation": "sc:painting",
            "annotatedBy": {
                "name": "OCR"
            },
            "resource": {
                "@type": "cnt:ContentAsText",
                "format": "text/html",
                "chars": "<span id='335df2a5-7b86-49c5-8d09-bbdef1309c2e' data-letter-spacing='0.16234276729559746'>\u00f6rn</span>",
                "language": "en"
            },
            "on": {
                "full": "https://readux2.ecdsdev.org/iiif/v2/17447788.4942.emory.edu/canvas/17447788.4942.emory.edu$118",
                "@type": "oa:SpecificResource",
                "within": {
                    "@id": "https://readux2.ecdsdev.org/iiif/v2/17447788.4942.emory.edu/manifest",
                    "@type": "sc:Manifest"
                },
                "selector": {
                    "@type": "oa:FragmentSelector",
                    "value": "xywh=749,1707,53,29",
                    "item": {
                        "@type": "oa:FragmentSelector"
                    }
                }
            },
            "stylesheet": {
                "type": "CssStylesheet",
                "value": ".anno-335df2a5-7b86-49c5-8d09-bbdef1309c2e: { height: 29px; width: 53px; font-size: 18.125px; }"
            }
        },
        {
            "@context": "http://iiif.io/api/presentation/2/context.json",
            "@id": "f417dba1-55d8-4126-bc32-5b605d8cc7c7",
            "@type": "oa:Annotation",
            "motivation": "sc:painting",
            "annotatedBy": {
                "name": "OCR"
            },
            "resource": {
                "@type": "cnt:ContentAsText",
                "format": "text/html",
                "chars": "<span id='f417dba1-55d8-4126-bc32-5b605d8cc7c7' data-letter-spacing='0.14717741935483872'>de</span>",
                "language": "en"
            },
            "on": {
                "full": "https://readux2.ecdsdev.org/iiif/v2/17447788.4942.emory.edu/canvas/17447788.4942.emory.edu$118",
                "@type": "oa:SpecificResource",
                "within": {
                    "@id": "https://readux2.ecdsdev.org/iiif/v2/17447788.4942.emory.edu/manifest",
                    "@type": "sc:Manifest"
                },
                "selector": {
                    "@type": "oa:FragmentSelector",
                    "value": "xywh=821,1702,31,35",
                    "item": {
                        "@type": "oa:FragmentSelector"
                    }
                }
            },
            "stylesheet": {
                "type": "CssStylesheet",
                "value": ".anno-f417dba1-55d8-4126-bc32-5b605d8cc7c7: { height: 35px; width: 31px; font-size: 21.875px; }"
            }
        },
        {
            "@context": "http://iiif.io/api/presentation/2/context.json",
            "@id": "b1a9c045-f4cc-41a3-a4af-316e5bbca54f",
            "@type": "oa:Annotation",
            "motivation": "sc:painting",
            "annotatedBy": {
                "name": "OCR"
            },
            "resource": {
                "@type": "cnt:ContentAsText",
                "format": "text/html",
                "chars": "<span id='b1a9c045-f4cc-41a3-a4af-316e5bbca54f' data-letter-spacing='0.024872448979591837'>Moortel</span>",
                "language": "en"
            },
            "on": {
                "full": "https://readux2.ecdsdev.org/iiif/v2/17447788.4942.emory.edu/canvas/17447788.4942.emory.edu$118",
                "@type": "oa:SpecificResource",
                "within": {
                    "@id": "https://readux2.ecdsdev.org/iiif/v2/17447788.4942.emory.edu/manifest",
                    "@type": "sc:Manifest"
                },
                "selector": {
                    "@type": "oa:FragmentSelector",
                    "value": "xywh=868,1700,98,37",
                    "item": {
                        "@type": "oa:FragmentSelector"
                    }
                }
            },
            "stylesheet": {
                "type": "CssStylesheet",
                "value": ".anno-b1a9c045-f4cc-41a3-a4af-316e5bbca54f: { height: 37px; width: 98px; font-size: 23.125px; }"
            }
        },
        {
            "@context": "http://iiif.io/api/presentation/2/context.json",
            "@id": "1f6562aa-db2c-459e-b797-b2aecf813f45",
            "@type": "oa:Annotation",
            "motivation": "sc:painting",
            "annotatedBy": {
                "name": "OCR"
            },
            "resource": {
                "@type": "cnt:ContentAsText",
                "format": "text/html",
                "chars": "<span id='1f6562aa-db2c-459e-b797-b2aecf813f45' data-letter-spacing='0.1487676056338028'><vaa</span>",
                "language": "en"
            },
            "on": {
                "full": "https://readux2.ecdsdev.org/iiif/v2/17447788.4942.emory.edu/canvas/17447788.4942.emory.edu$118",
                "@type": "oa:SpecificResource",
                "within": {
                    "@id": "https://readux2.ecdsdev.org/iiif/v2/17447788.4942.emory.edu/manifest",
                    "@type": "sc:Manifest"
                },
                "selector": {
                    "@type": "oa:FragmentSelector",
                    "value": "xywh=982,1709,71,23",
                    "item": {
                        "@type": "oa:FragmentSelector"
                    }
                }
            },
            "stylesheet": {
                "type": "CssStylesheet",
                "value": ".anno-1f6562aa-db2c-459e-b797-b2aecf813f45: { height: 23px; width: 71px; font-size: 14.375px; }"
            }
        },
        {
            "@context": "http://iiif.io/api/presentation/2/context.json",
            "@id": "016853a1-11d3-48d2-a0ad-623f371f2a20",
            "@type": "oa:Annotation",
            "motivation": "sc:painting",
            "annotatedBy": {
                "name": "OCR"
            },
            "resource": {
                "@type": "cnt:ContentAsText",
                "format": "text/html",
                "chars": "<span id='016853a1-11d3-48d2-a0ad-623f371f2a20' data-letter-spacing='0.19302721088435376'>een</span>",
                "language": "en"
            },
            "on": {
                "full": "https://readux2.ecdsdev.org/iiif/v2/17447788.4942.emory.edu/canvas/17447788.4942.emory.edu$118",
                "@type": "oa:SpecificResource",
                "within": {
                    "@id": "https://readux2.ecdsdev.org/iiif/v2/17447788.4942.emory.edu/manifest",
                    "@type": "sc:Manifest"
                },
                "selector": {
                    "@type": "oa:FragmentSelector",
                    "value": "xywh=1075,1710,49,22",
                    "item": {
                        "@type": "oa:FragmentSelector"
                    }
                }
            },
            "stylesheet": {
                "type": "CssStylesheet",
                "value": ".anno-016853a1-11d3-48d2-a0ad-623f371f2a20: { height: 22px; width: 49px; font-size: 13.75px; }"
            }
        },
        {
            "@context": "http://iiif.io/api/presentation/2/context.json",
            "@id": "f2d168e1-c238-4451-a79c-23195def220c",
            "@type": "oa:Annotation",
            "motivation": "sc:painting",
            "annotatedBy": {
                "name": "OCR"
            },
            "resource": {
                "@type": "cnt:ContentAsText",
                "format": "text/html",
                "chars": "<span id='f2d168e1-c238-4451-a79c-23195def220c' data-letter-spacing='0.11979166666666667'>bom.</span>",
                "language": "en"
            },
            "on": {
                "full": "https://readux2.ecdsdev.org/iiif/v2/17447788.4942.emory.edu/canvas/17447788.4942.emory.edu$118",
                "@type": "oa:SpecificResource",
                "within": {
                    "@id": "https://readux2.ecdsdev.org/iiif/v2/17447788.4942.emory.edu/manifest",
                    "@type": "sc:Manifest"
                },
                "selector": {
                    "@type": "oa:FragmentSelector",
                    "value": "xywh=1148,1696,84,35",
                    "item": {
                        "@type": "oa:FragmentSelector"
                    }
                }
            },
            "stylesheet": {
                "type": "CssStylesheet",
                "value": ".anno-f2d168e1-c238-4451-a79c-23195def220c: { height: 35px; width: 84px; font-size: 21.875px; }"
            }
        }
    ]
}